README.md
setup.py
sprites/__init__.py
sprites.egg-info/PKG-INFO
sprites.egg-info/SOURCES.txt
sprites.egg-info/dependency_links.txt
sprites.egg-info/not-zip-safe
sprites.egg-info/requires.txt
sprites.egg-info/top_level.txt