Metadata-Version: 2.1
Name: sprites
Version: 1.724
Summary: Python Sprites Module for make introductory animations and games and educational purpose。It mainly provides Sprite class inherited from Turtle class。Can be applied to the teaching of elementary mathematics。Pyhton的精灵模块，为教育目的而制作启蒙动画与游戏。主要提供继承自Turtle类的Sprite类,Key类,Mouse类等及一些工具函数,如洪水填充命令,几何相关命令。它支持像素级碰撞检测命令及增强的图章命令等等。由于增加了一些初等几何命令，如求三角形的重心，作中垂线，所以也可应用于初等数学几何的教学。作者：李兴球。微信:scratch8，公众号：异编程。网址： www.lixingqiu.com
Home-page: http://www.lixingqiu.com
Author: lixingqiu
Author-email: 406273900@qq.com
License: MIT
Keywords: creative game pygame turtle animation sprite geometry math Elementary Mathematics Teaching
Platform: UNKNOWN
